[
    {
        "id": "R_kgDOMc640w",
        "isPrivate": 2,
        "name": "P3_Digital-Origins",
        "url": "https://github.com/JohaneDecamps/P3_Digital-Origins"
    },
    {
        "id": "R_kgDOMWtuRA",
        "isPrivate": 2,
        "name": "cp4_moone",
        "url": "https://github.com/JohaneDecamps/cp4_moone"
    },
    {
        "id": "R_kgDOMKe2qQ",
        "isPrivate": 1,
        "name": "Moone-Ceramiques",
        "url": "https://github.com/JohaneDecamps/Moone-Ceramiques"
    },
    {
        "id": "R_kgDOMTbhXw",
        "isPrivate": 2,
        "name": "security",
        "url": "https://github.com/JohaneDecamps/security"
    },
    {
        "id": "R_kgDOMQ_lhQ",
        "isPrivate": 2,
        "name": "quest-security",
        "url": "https://github.com/JohaneDecamps/quest-security"
    },
    {
        "id": "R_kgDOMKF3gw",
        "isPrivate": 2,
        "name": "No-made",
        "url": "https://github.com/JohaneDecamps/No-made"
    },
    {
        "id": "R_kgDOL_Bilg",
        "isPrivate": 2,
        "name": "ProjetHarmonia",
        "url": "https://github.com/JohaneDecamps/ProjetHarmonia"
    },
    {
        "id": "R_kgDOL1LqzA",
        "isPrivate": 2,
        "name": "Homelyfood-P2",
        "url": "https://github.com/JohaneDecamps/Homelyfood-P2"
    },
    {
        "id": "R_kgDOL1LqSg",
        "isPrivate": 2,
        "name": "Ho",
        "url": "https://github.com/JohaneDecamps/Ho"
    },
    {
        "id": "R_kgDOL1LJCw",
        "isPrivate": 2,
        "name": "Homelyfood",
        "url": "https://github.com/JohaneDecamps/Homelyfood"
    },
    {
        "id": "R_kgDOLzk3Sw",
        "isPrivate": 1,
        "name": "Test",
        "url": "https://github.com/JohaneDecamps/Test"
    },
    {
        "id": "R_kgDOLu2Zww",
        "isPrivate": 2,
        "name": "dotenv",
        "url": "https://github.com/JohaneDecamps/dotenv"
    },
    {
        "id": "R_kgDOLlRSzA",
        "isPrivate": 2,
        "name": "pok-dex",
        "url": "https://github.com/JohaneDecamps/pok-dex"
    },
    {
        "id": "R_kgDOLib-Eg",
        "isPrivate": 2,
        "name": "wilders",
        "url": "https://github.com/JohaneDecamps/wilders"
    },
    {
        "id": "R_kgDOLeUcRA",
        "isPrivate": 2,
        "name": "quete5",
        "url": "https://github.com/JohaneDecamps/quete5"
    },
    {
        "id": "R_kgDOLeUPBw",
        "isPrivate": 2,
        "name": "website-flow",
        "url": "https://github.com/JohaneDecamps/website-flow"
    },
    {
        "id": "R_kgDOLcaWFw",
        "isPrivate": 2,
        "name": "wild-project",
        "url": "https://github.com/JohaneDecamps/wild-project"
    },
    {
        "id": "R_kgDOLbA5og",
        "isPrivate": 2,
        "name": "HelloWorld",
        "url": "https://github.com/JohaneDecamps/HelloWorld"
    },
    {
        "id": "R_kgDOLYRcWg",
        "isPrivate": 2,
        "name": "workshop-3",
        "url": "https://github.com/JohaneDecamps/workshop-3"
    },
    {
        "id": "R_kgDOLbE9dA",
        "isPrivate": 2,
        "name": "my-awesome-project",
        "url": "https://github.com/JohaneDecamps/my-awesome-project"
    }
]